async_healthcheck/__init__.py
async_healthcheck/main.py
async_healthcheck-0.7.0.dist-info/LICENSE
async_healthcheck-0.7.0.dist-info/METADATA
async_healthcheck-0.7.0.dist-info/WHEEL
async_healthcheck-0.7.0.dist-info/RECORD
