Metadata-Version: 2.1
Name: async-healthcheck
Version: 0.7.0
Summary: A compact asynchronous healthcheck using only the standard library
License: Apache-2.0
Author: Evgeny Aleshin
Requires-Python: >=3.9,<4.0
Classifier: License :: OSI Approved :: Apache Software License
Classifier: Programming Language :: Python :: 3
Classifier: Programming Language :: Python :: 3.9
Classifier: Programming Language :: Python :: 3.10
Classifier: Programming Language :: Python :: 3.11
Classifier: Programming Language :: Python :: 3.12
